{
    "display": {
      "icon": {
        "id": "minecraft:iron_ore"
      },
      "title": "Tired of usinng lame, sad metal?",
      "description": "Introducing iron",
      "frame": "task",
      "show_toast": true,
      "announce_to_chat": true,
      "hidden": false
    },
    "parent": "ages_of_old:copper_pickaxe",
    "criteria": {
      "requirement": {
        "trigger": "minecraft:inventory_changed",
        "conditions": {
          "items": [
            {
              "items": "minecraft:raw_iron"
            }
          ]
        }
      }
    },
    "rewards": {}
  }
  